odoo/addons/account_mass_reconcile_by_purchase_line/README.rst
odoo/addons/account_mass_reconcile_by_purchase_line/__init__.py
odoo/addons/account_mass_reconcile_by_purchase_line/__manifest__.py
odoo/addons/account_mass_reconcile_by_purchase_line/i18n/account_mass_reconcile_by_purchase_line.pot
odoo/addons/account_mass_reconcile_by_purchase_line/i18n/ar.po
odoo/addons/account_mass_reconcile_by_purchase_line/models/__init__.py
odoo/addons/account_mass_reconcile_by_purchase_line/models/advanced_reconciliation.py
odoo/addons/account_mass_reconcile_by_purchase_line/models/base_advanced_reconciliation.py
odoo/addons/account_mass_reconcile_by_purchase_line/models/mass_reconcile.py
odoo/addons/account_mass_reconcile_by_purchase_line/static/description/icon.png
odoo/addons/account_mass_reconcile_by_purchase_line/views/mass_reconcile.xml
odoo11_addon_account_mass_reconcile_by_purchase_line-11.0.1.0.0.99.dev5.dist-info/METADATA
odoo11_addon_account_mass_reconcile_by_purchase_line-11.0.1.0.0.99.dev5.dist-info/RECORD
odoo11_addon_account_mass_reconcile_by_purchase_line-11.0.1.0.0.99.dev5.dist-info/WHEEL
odoo11_addon_account_mass_reconcile_by_purchase_line-11.0.1.0.0.99.dev5.dist-info/top_level.txt
